vivado_nit_projects/mod5_counter/mod5_counter.srcs/sources_1/new/mod5_counter.v
`timescale 1ns / 1ps
//////////////////////////////////////////////////////////////////////////////////
// Company: 
// Engineer: 
// 
// Create Date: 11/19/2025 01:46:34 PM
// Design Name: 
// Module Name: mod5_counter
// Project Name: 
// Target Devices: 
// Tool Versions: 
// Description: 
// 
// Dependencies: 
// 
// Revision:
// Revision 0.01 - File Created
// Additional Comments:
// 
//////////////////////////////////////////////////////////////////////////////////


module mod5_counter(
    input up_mod5,rst_mod5,clk,
    output reg [2:0] out_mod5
    );
    
    initial begin
        out_mod5 = 3'b000;
        
    end
    
    always@(posedge clk or posedge rst_mod5)
    begin
        if (rst_mod5) begin
            out_mod5 <= 3'b000;
        end
        else begin
            if (up_mod5)
            begin
                if(out_mod5 >= 3'b101)
                begin
                    out_mod5 <= 3'b000;
                end
                else
                begin
                    out_mod5 <= out_mod5 + 3'b001;
                end
            end
        
        end
             
    end
    
endmodule

vivado_nit_projects/mod5_counter/mod5_counter.srcs/sim_1/new/tb_mod5_counter.v
`timescale 1ns / 1ps
//////////////////////////////////////////////////////////////////////////////////
// Company: 
// Engineer: 
// 
// Create Date: 11/19/2025 01:53:06 PM
// Design Name: 
// Module Name: tb_mod5_counter
// Project Name: 
// Target Devices: 
// Tool Versions: 
// Description: 
// 
// Dependencies: 
// 
// Revision:
// Revision 0.01 - File Created
// Additional Comments:
// 
//////////////////////////////////////////////////////////////////////////////////


module tb_mod5_counter(

    );
    
    reg tb_up_mod5, rst_up_mod5, tb_clk;
    wire [2:0] tb_out_mod5;
    
    mod5_counter counter_0(
        .up_mod5(tb_up_mod5),.rst_mod5(rst_up_mod5),.clk(tb_clk),
        .out_mod5(tb_out_mod5)
    );
    
    initial begin
        tb_up_mod5  = 1'b0;
        rst_up_mod5 = 1'b0;
        tb_clk      = 1'b0;
        $monitor("time=%g\t, clk=%b, rst=%b, up=%b, count=%d",$time,tb_clk,rst_up_mod5,tb_up_mod5,tb_out_mod5);
        #10
        tb_up_mod5  = 1'b1; #10
        tb_up_mod5  = 1'b0; #10
        tb_up_mod5  = 1'b1; #20
        tb_up_mod5  = 1'b0; #10
        tb_up_mod5  = 1'b1; #10
        tb_up_mod5  = 1'b0; #50
        tb_up_mod5  = 1'b1; #20
        tb_up_mod5  = 1'b0; #10
        tb_up_mod5  = 1'b1; #30
        tb_up_mod5  = 1'b0; #70
        tb_up_mod5  = 1'b1; #37
        rst_up_mod5 = 1'b1; #20
        tb_up_mod5  = 1'b0; #10
        rst_up_mod5 = 1'b0; #10
        tb_up_mod5  = 1'b1; #70
        tb_up_mod5  = 1'b0; #10;
        $finish;
    end
    
    initial begin
        $dumpfile("mod5_counter.vcd");
        $dumpvars(0,tb_mod5_counter);
    end
    
    always #10 tb_clk = ~tb_clk;
endmodule

vivado_nit_projects/mod5_counter/mod5_counter.sim/sim_1/behav/xsim/mod5_counter.vcd
$date
   Sun Dec 14 17:09:26 2025
$end
$version
  2022.2
$end
$timescale
  1ps
$end
$scope module tb_mod5_counter $end
$var reg 1 ! tb_up_mod5 $end
$var reg 1 " rst_up_mod5 $end
$var reg 1 # tb_clk $end
$var wire 3 $ tb_out_mod5 [2:0] $end
$scope module counter_0 $end
$var wire 1 % up_mod5 $end
$var wire 1 & rst_mod5 $end
$var wire 1 ' clk $end
$var reg 3 ( out_mod5 [2:0] $end
$upscope $end
$upscope $end
$enddefinitions $end
#0
$dumpvars
0!
0"
0#
b0 $
0%
0&
0'
b0 (
$end
#10000
1!
1#
b1 $
1%
1'
b1 (
#20000
0!
0#
0%
0'
#30000
1!
1#
b10 $
1%
1'
b10 (
#40000
0#
0'
#50000
0!
1#
0%
1'
#60000
1!
0#
1%
0'
#70000
0!
1#
0%
1'
#80000
0#
0'
#90000
1#
1'
#100000
0#
0'
#110000
1#
1'
#120000
1!
0#
1%
0'
#130000
1#
b11 $
1'
b11 (
#140000
0!
0#
0%
0'
#150000
1!
1#
b100 $
1%
1'
b100 (
#160000
0#
0'
#170000
1#
b101 $
1'
b101 (
#180000
0!
0#
0%
0'
#190000
1#
1'
#200000
0#
0'
#210000
1#
1'
#220000
0#
0'
#230000
1#
1'
#240000
0#
0'
#250000
1!
1#
b0 $
1%
1'
b0 (
#260000
0#
0'
#270000
1#
b1 $
1'
b1 (
#280000
0#
0'
#287000
1"
b0 $
1&
b0 (
#290000
1#
1'
b0 (
#300000
0#
0'
#307000
0!
0%
#310000
1#
1'
b0 (
#317000
0"
0&
#320000
0#
0'
#327000
1!
1%
#330000
1#
b1 $
1'
b1 (
#340000
0#
0'
#350000
1#
b10 $
1'
b10 (
#360000
0#
0'
#370000
1#
b11 $
1'
b11 (
#380000
0#
0'
#390000
1#
b100 $
1'
b100 (
#397000
0!
0%
